{
    "https://github.com/micahvdm/profiler": [
        "profiler.lv2"
    ],
    "https://github.com/x42/tuna.lv2": [
        "tuna.lv2"
    ],
    "https://github.com/thunderox/triceratops": [
        "triceratops.lv2"
    ],
    "https://github.com/x42/tinyamp.lv2": [
        "tinygain.lv2"
    ],
    "https://github.com/x42/zconvo.lv2": [
        "zeroconvo.lv2"
    ],
    "https://github.com/brummer10/screcord.lv2": [
        "sc_record.lv2"
    ],
    "https://github.com/falkTX/rubberband": [
        "rubberband.lv2"
    ],
    "https://github.com/moddevices/caps-lv2": [
        "mod-caps-AmpVTS.lv2",
        "mod-caps-AutoFilter.lv2",
        "mod-caps-CabinetIII.lv2",
        "mod-caps-CabinetIV.lv2",
        "mod-caps-CEO.lv2",
        "mod-caps-ChorusI.lv2",
        "mod-caps-Click.lv2",
        "mod-caps-Compress.lv2",
        "mod-caps-CompressX2.lv2",
        "mod-caps-Eq4p.lv2",
        "mod-caps-Eq10.lv2",
        "mod-caps-Eq10X2.lv2",
        "mod-caps-EqFA4p.lv2",
        "mod-caps-Fractal.lv2",
        "mod-caps-Narrower.lv2",
        "mod-caps-Noisegate.lv2",
        "mod-caps-PhaserII.lv2",
        "mod-caps-Plate.lv2",
        "mod-caps-PlateX2.lv2",
        "mod-caps-Saturate.lv2",
        "mod-caps-Scape.lv2",
        "mod-caps-Sin.lv2",
        "mod-caps-Spice.lv2",
        "mod-caps-SpiceX2.lv2",
        "mod-caps-ToneStack.lv2",
        "mod-caps-White.lv2",
        "mod-caps-Wider.lv2"
    ],
    "https://github.com/moddevices/mda-lv2": [
        "mod-mda-Ambience.lv2",
        "mod-mda-Bandisto.lv2",
        "mod-mda-BeatBox.lv2",
        "mod-mda-Combo.lv2",
        "mod-mda-DeEss.lv2",
        "mod-mda-Degrade.lv2",
        "mod-mda-Delay.lv2",
        "mod-mda-Detune.lv2",
        "mod-mda-Dither.lv2",
        "mod-mda-DubDelay.lv2",
        "mod-mda-DX10.lv2",
        "mod-mda-Dynamics.lv2",
        "mod-mda-EPiano.lv2",
        "mod-mda-Image.lv2",
        "mod-mda-JX10.lv2",
        "mod-mda-Leslie.lv2",
        "mod-mda-Limiter.lv2",
        "mod-mda-Loudness.lv2",
        "mod-mda-MultiBand.lv2",
        "mod-mda-Overdrive.lv2",
        "mod-mda-Piano.lv2",
        "mod-mda-RePsycho.lv2",
        "mod-mda-RezFilter.lv2",
        "mod-mda-RingMod.lv2",
        "mod-mda-RoundPan.lv2",
        "mod-mda-Shepard.lv2",
        "mod-mda-Splitter.lv2",
        "mod-mda-Stereo.lv2",
        "mod-mda-SubSynth.lv2",
        "mod-mda-TalkBox.lv2",
        "mod-mda-TestTone.lv2",
        "mod-mda-ThruZero.lv2",
        "mod-mda-Tracker.lv2",
        "mod-mda-Transient.lv2",
        "mod-mda-VocInput.lv2",
        "mod-mda-Vocoder.lv2"
    ],
    "https://github.com/moddevices/mod-distortion": [
        "mod-bigmuff.lv2",
        "mod-ds1.lv2"
    ],
    "https://github.com/moddevices/mod-pitchshifter": [
        "mod-2voices.lv2",
        "mod-capo.lv2",
        "mod-drop.lv2",
        "mod-harmonizer.lv2",
        "mod-harmonizer2.lv2",
        "mod-harmonizercs.lv2",
        "mod-supercapo.lv2",
        "mod-superwhammy.lv2"
    ],
    "https://github.com/moddevices/mod-utilities": [
        "mod-bpf.lv2",
        "mod-crossover2.lv2",
        "mod-crossover3.lv2",
        "mod-gain.lv2",
        "mod-gain2x2.lv2",
        "mod-hpf.lv2",
        "mod-lpf.lv2",
        "mod-switchbox2.lv2",
        "mod-switchtrigger4.lv2",
        "mod-toggleswitch4.lv2"
    ],
    "https://github.com/moddevices/mod-cv-plugins": [
        "mod-midi-to-cv-poly.lv2",
        "mod-midi-to-cv-mono.lv2",
        "mod-button-to-cv.lv2",
        "mod-audio-to-cv.lv2"
    ],
    "https://github.com/brummer10/GxSVT.lv2": [
    	"gx_ampegsvt.lv2"
    ]
}